{
  "_class": "text",
  "attributedString": {
    "_class": "attributedString",
    "attributes": [
      {
        "_class": "stringAttribute",
        "attributes": {
          "MSAttributedStringColorAttribute": {
            "_class": "color",
            "alpha": 1,
            "blue": 0,
            "green": 0,
            "red": 0
          },
          "MSAttributedStringFontAttribute": {
            "_class": "fontDescriptor",
            "attributes": {
              "name": "Lato-Regular",
              "size": 24
            }
          },
          "ligature": 0,
          "paragraphStyle": {
            "_class": "paragraphStyle",
            "alignment": 0,
            "allowsDefaultTighteningForTruncation": 0,
            "maximumLineHeight": 32,
            "minimumLineHeight": 32
          }
        },
        "length": 23,
        "location": 0
      }
    ],
    "string": "Headline / Lato Regular"
  },
  "automaticallyDrawOnUnderlyingPath": false,
  "booleanOperation": 0,
  "clippingMaskMode": 0,
  "do_objectID": "B5F7F693-625F-46E3-89DE-EAADA18EDA2C",
  "dontSynchroniseWithSymbol": false,
  "exportOptions": {
    "_class": "exportOptions",
    "exportFormats": [
    ],
    "includedLayerIds": [
    ],
    "layerOptions": 0,
    "shouldTrim": false
  },
  "frame": {
    "_class": "rect",
    "constrainProportions": false,
    "do_objectID": "CEC1C43A-612B-4239-BC9A-4DFE0EA575C8",
    "height": 32,
    "width": 246,
    "x": -1031,
    "y": 4933
  },
  "glyphBounds": "{{2, 7}, {244, 23}}",
  "hasClippingMask": false,
  "isFixedToViewport": false,
  "isFlippedHorizontal": false,
  "isFlippedVertical": false,
  "isLocked": false,
  "isVisible": true,
  "layerListExpandedType": 0,
  "lineSpacingBehaviour": 2,
  "name": "Headline / Lato Regular",
  "nameIsFixed": true,
  "resizingConstraint": 11,
  "resizingType": 0,
  "rotation": 0,
  "sharedStyleID": "02A51D68-4C30-4D1D-BC9E-99731163D57D",
  "shouldBreakMaskChain": false,
  "style": {
    "_class": "style",
    "contextSettings": {
      "_class": "graphicsContextSettings",
      "blendMode": 0,
      "do_objectID": "231FB55B-F587-4885-AEC1-FE0CE6332DE3",
      "opacity": 0.3799999952316284
    },
    "do_objectID": "E30D6082-350E-49FD-A13E-F95C823D7613",
    "endMarkerType": 0,
    "fills": [
      {
        "_class": "fill",
        "color": {
          "_class": "color",
          "alpha": 0.88,
          "blue": 0,
          "green": 0,
          "red": 0
        },
        "fillType": 0,
        "isEnabled": false,
        "noiseIndex": 0,
        "noiseIntensity": 0,
        "patternFillType": 1,
        "patternTileScale": 1
      }
    ],
    "miterLimit": 10,
    "startMarkerType": 0,
    "textStyle": {
      "_class": "textStyle",
      "do_objectID": "B82D2052-B74D-43C8-A276-B55732B22001",
      "encodedAttributes": {
        "MSAttributedStringColorAttribute": {
          "_class": "color",
          "alpha": 1,
          "blue": 0,
          "green": 0,
          "red": 0
        },
        "MSAttributedStringFontAttribute": {
          "_class": "fontDescriptor",
          "attributes": {
            "name": "Lato-Regular",
            "size": 24
          }
        },
        "ligature": 0,
        "paragraphStyle": {
          "_class": "paragraphStyle",
          "alignment": 0,
          "allowsDefaultTighteningForTruncation": 0,
          "maximumLineHeight": 32,
          "minimumLineHeight": 32
        }
      },
      "verticalAlignment": 0
    },
    "windingRule": 1
  },
  "textBehaviour": 0
}