{
  "_class": "text",
  "attributedString": {
    "_class": "attributedString",
    "attributes": [
      {
        "_class": "stringAttribute",
        "attributes": {
          "MSAttributedStringColorAttribute": {
            "_class": "color",
            "alpha": 1,
            "blue": 0,
            "green": 0,
            "red": 0
          },
          "MSAttributedStringFontAttribute": {
            "_class": "fontDescriptor",
            "attributes": {
              "name": "Lato-Bold",
              "size": 24
            }
          },
          "kerning": 0.3,
          "ligature": 0,
          "paragraphStyle": {
            "_class": "paragraphStyle",
            "alignment": 0,
            "allowsDefaultTighteningForTruncation": 0,
            "maximumLineHeight": 24,
            "minimumLineHeight": 24
          }
        },
        "length": 9,
        "location": 0
      }
    ],
    "string": "Nutrition"
  },
  "automaticallyDrawOnUnderlyingPath": false,
  "booleanOperation": -1,
  "clippingMaskMode": 0,
  "do_objectID": "9517DF6E-5155-4921-923E-5FA56AEB4B5A",
  "dontSynchroniseWithSymbol": false,
  "frame": {
    "_class": "rect",
    "constrainProportions": false,
    "do_objectID": "FB83FE45-E81D-4D9B-B7DA-F8828DA862D9",
    "height": 24,
    "width": 104,
    "x": 389,
    "y": 1131
  },
  "glyphBounds": "{{1, 3}, {101, 19}}",
  "hasClippingMask": false,
  "isFixedToViewport": false,
  "isFlippedHorizontal": false,
  "isFlippedVertical": false,
  "isLocked": false,
  "isVisible": true,
  "layerListExpandedType": 0,
  "lineSpacingBehaviour": 2,
  "name": "00 UI Greys / Table Head / Black / 54 Left Copy 4",
  "nameIsFixed": true,
  "resizingConstraint": 9,
  "resizingType": 0,
  "rotation": 0,
  "sharedStyleID": "CCF31051-63A5-4A37-B086-B951926A333D",
  "shouldBreakMaskChain": false,
  "style": {
    "_class": "style",
    "contextSettings": {
      "_class": "graphicsContextSettings",
      "blendMode": 0,
      "opacity": 0.87
    },
    "do_objectID": "2A552BFF-A1CB-4D16-A9FA-992C62420063",
    "endMarkerType": 0,
    "fills": [
      {
        "_class": "fill",
        "color": {
          "_class": "color",
          "alpha": 0.88,
          "blue": 0,
          "green": 0,
          "red": 0
        },
        "fillType": 0,
        "isEnabled": false,
        "noiseIndex": 0,
        "noiseIntensity": 0,
        "patternFillType": 1,
        "patternTileScale": 1
      }
    ],
    "miterLimit": 10,
    "startMarkerType": 0,
    "textStyle": {
      "_class": "textStyle",
      "encodedAttributes": {
        "MSAttributedStringColorAttribute": {
          "_class": "color",
          "alpha": 1,
          "blue": 0,
          "green": 0,
          "red": 0
        },
        "MSAttributedStringFontAttribute": {
          "_class": "fontDescriptor",
          "attributes": {
            "name": "Lato-Bold",
            "size": 24
          }
        },
        "kerning": 0.3,
        "ligature": 0,
        "paragraphStyle": {
          "_class": "paragraphStyle",
          "alignment": 0,
          "allowsDefaultTighteningForTruncation": 0,
          "maximumLineHeight": 24,
          "minimumLineHeight": 24
        }
      },
      "verticalAlignment": 0
    },
    "windingRule": 1
  },
  "textBehaviour": 0
}